sharepoint_utils/ModuleGet.py
sharepoint_utils/ModuleRead.py
sharepoint_utils/__init__.py
sharepoint_utils/main.py
sharepoint_utils-2.0.dist-info/LICENSE.txt
sharepoint_utils-2.0.dist-info/METADATA
sharepoint_utils-2.0.dist-info/WHEEL
sharepoint_utils-2.0.dist-info/top_level.txt
sharepoint_utils-2.0.dist-info/RECORD
