Metadata-Version: 2.1
Name: sharepoint-utils
Version: 2.0
Summary: Utility functions for working with SharePoint
Author: Omkar Sutar
Classifier: Programming Language :: Python :: 3
Classifier: License :: OSI Approved :: MIT License
Classifier: Operating System :: OS Independent
License-File: LICENSE.txt
Requires-Dist: pandas
Requires-Dist: Office365-REST-Python-Client
